embedded_modbus/ModulConnector.py
embedded_modbus/__init__.py
embedded_modbus/utils.py
embedded_modbus-0.1.dist-info/METADATA
embedded_modbus-0.1.dist-info/WHEEL
embedded_modbus-0.1.dist-info/top_level.txt
embedded_modbus-0.1.dist-info/RECORD
